elro/__init__.py
elro/api.py
elro/auth.py
elro/command.py
elro/device.py
elro/utils.py
lib_elro_connects-0.6.2.0.data/data/share/lib-elro-connects/cloud_login_demo.py
lib_elro_connects-0.6.2.0.data/data/share/lib-elro-connects/fire_alarm_demo.py
lib_elro_connects-0.6.2.0.data/data/share/lib-elro-connects/socket_demo.py
lib_elro_connects-0.6.2.0.dist-info/licenses/LICENSE
lib_elro_connects-0.6.2.0.dist-info/METADATA
lib_elro_connects-0.6.2.0.dist-info/WHEEL
lib_elro_connects-0.6.2.0.dist-info/top_level.txt
lib_elro_connects-0.6.2.0.dist-info/RECORD
