Metadata-Version: 2.4
Name: lib-elro-connects
Version: 0.6.2.0
Summary: Elro Connects P1 API
Home-page: https://github.com/jbouwh/lib-elro-connects
Author: Jan Bouwhuis
Author-email: jan@jbsoft.nl
License: MIT Licence
Classifier: Development Status :: 4 - Beta
Classifier: Topic :: Home Automation
Classifier: Programming Language :: Python :: 3.9
Classifier: License :: OSI Approved :: MIT License
Classifier: Operating System :: OS Independent
Requires-Python: >=3.9
License-File: LICENSE
Provides-Extra: test
Requires-Dist: pytest; extra == "test"
Requires-Dist: pytest-cov; extra == "test"
Requires-Dist: asynctest; extra == "test"
Requires-Dist: pytest-asyncio; extra == "test"
Dynamic: author
Dynamic: author-email
Dynamic: classifier
Dynamic: description
Dynamic: description-content-type
Dynamic: home-page
Dynamic: license
Dynamic: license-file
Dynamic: requires-python
Dynamic: summary
